{
  "questionId": "062f86db",
  "correctAnswer": "C",
  "section": "Math",
  "steps": [
    {
      "title": "Fastest path: graph or solve the equation",
      "content": "Type the equation into Desmos as written:<br/>$$5{x}^{2}-37x-24=0$$Graph it and use the visible intercept, root, or vertex the question asks for. The requested value is $8$.",
      "desmosExpressions": [
        "5{x}^{2}-37x-24=0"
      ]
    },
    {
      "title": "Factor the quadratic",
      "content": "Find two factors of $5x^2-37x-24$:<br/>$$5x^2-37x-24=(5x+3)(x-8)$$"
    },
    {
      "title": "Set each factor equal to zero",
      "content": "$$(5x+3)(x-8)=0$$<br/>So either $5x+3=0$ or $x-8=0$. The solutions are:<br/>$$x=-\\frac{3}{5}\\quad\\text{or}\\quad x=8$$"
    },
    {
      "title": "Pick the positive solution",
      "content": "The positive solution is $8$."
    }
  ]
}
