{"questionId": "07bcecac", "correctAnswer": "C", "section": "Math", "steps": [{"title": "Decode the function parameters", "content": "The function $P(t) = 24.8(1.036)^t$ has:<br/><ul><li>Input $t$ = <strong>years after 1984</strong></li><li>Output $P(t)$ = <strong>population in millions</strong></li></ul>"}, {"title": "Interpret the value $P(8) = 32.91$", "content": "The statement $P(8) \\approx 32.91$ means that when $t = 8$, the population is 32.91 million.<br/><br/>Since $t = 8$ corresponds to 8 years after 1984, we conclude: <strong>8 years after 1984, the predicted population is approximately 32.91 million.</strong> That matches choice C — <strong>C</strong> is correct."}]}