{
  "questionId": "0a5f1b28-e866-44fd-85d1-c7684ad9e576_19",
  "correctAnswer": "C",
  "section": "Reading and Writing",
  "steps": [
    {
      "title": "Spot the Relationship Between Description and Name",
      "content": "The sentence introduces a person by pairing a general description (\u201cNigerian expressionist painter\u201d) with a specific name (\u201cGani Odutokun\u201d)."
    },
    {
      "title": "Apply the Rule for Punctuation",
      "content": "When the description applies to multiple people, the specific name must remain attached to the description to identify which person is meant. No commas should separate them. The other choices either fragment the sentence with a period (B) or add unnecessary commas (A and D).<br/><br/>That matches choice C \u2014 <strong>C</strong> is correct."
    }
  ]
}