{
  "questionId": "2ecbcc31-a047-4184-8f07-5ee89663c904_5",
  "correctAnswer": "D",
  "section": "Reading and Writing",
  "steps": [
    {
      "title": "Identify what the question needs",
      "content": "The question asks for the best description of the <em>overall structure</em> of the text. Map what each part does: the first three sentences introduce a customization trend and its benefits; the final sentence (signaled by <strong>Still</strong>) introduces a challenge companies face."
    },
    {
      "title": "Eliminate the choices",
      "content": "<ul><li><strong>Choice A — It discusses several recent innovations in product manufacturing and then suggests some potential applications of those innovations.</strong>: the passage discusses one trend (customization), not multiple manufacturing innovations. &#10007;</li><li><strong>Choice B — It describes a company's recent success with new products and then explains multiple factors that may have contributed to that success.</strong>: no single company is described, and no specific company’s success story is told. &#10007;</li><li><strong>Choice C — It presents two contrasting product-marketing techniques and then provides examples of one of those techniques.</strong>: the passage does not compare two marketing techniques or give examples of one of them. &#10007;</li><li><strong>Choice D — It introduces a trend in consumer products and then explains how the trend both benefits and poses a challenge to companies.</strong>: the first three sentences introduce the customization trend and explain that companies profit and consumers pay more; the final sentence introduces the challenge of keeping costs low. &#10003;</li></ul><strong>D</strong> is correct."
    }
  ]
}
