{
  "questionId": "3926df58-b496-49f8-807d-ce478d37162e_21",
  "correctAnswer": "D",
  "section": "Reading and Writing",
  "steps": [
    {
      "title": "Identify the cause-effect relationship",
      "content": "The passage shows: he joined the Army, then served in the cavalry, then earned a place in history. The blank must express how the third action flows from the second."
    },
    {
      "title": "Match the causal link",
      "content": "The logical relationship is means-to-result: by serving in the cavalry, Johnson earned his place in history. The blank needs a transition signaling that the action in the preceding clause is how the result was achieved.<ul><li><strong>Choice A — usually,</strong>: signals habitual frequency, so fails — this is a specific individual's story, not a general pattern. ✗</li><li><strong>Choice B — for instance,</strong>: signals a specific example of a general claim, so fails — no general claim precedes this that cavalry service would illustrate. ✗</li><li><strong>Choice C — in any case,</strong>: signals a concession or change of subject, so fails — the sentence is building forward, not dismissing what came before. ✗</li><li><strong>Choice D — in doing so,</strong>: signals that through the preceding action he achieved the result, so fits — his cavalry service is how he earned his place in history. ✓</li></ul><strong>D</strong> is correct."
    }
  ]
}
