{
  "questionId": "406baf08-71da-41c0-bc3d-ddc2c25258ba_2",
  "correctAnswer": "A",
  "section": "Reading and Writing",
  "steps": [
    {
      "title": "Locate the definition clue",
      "content": "The colon after the blank signals that what follows defines it. The following clause says the delta is \u201ca constantly evolving network of channels \u2026\u201d \u2014 the key clue is the phrase \u201cconstantly evolving.\u201d"
    },
    {
      "title": "Match the meaning to the choices",
      "content": "Dynamic means constantly changing or evolving, which directly matches the clue \u201cconstantly evolving.\u201d The other choices either suggest unchangeableness, lack of change, or unrelated ideas, so they do not fit the context. That matches choice A \u2014 <strong>A</strong> is correct."
    }
  ]
}