{
  "questionId": "595615e1-f0a9-4cfd-a290-fb855094a94a_4",
  "correctAnswer": "B",
  "section": "Reading and Writing",
  "steps": [
    {
      "title": "Link damage to its source",
      "content": "The sentence says critics complimented the novel despite damage connected to Soviet censors. The blank needs a phrase meaning that the damage was caused or inflicted by those censors."
    },
    {
      "title": "Choose the caused-by phrase",
      "content": "Choice A suggests a gift, Choice C suggests allocation, and Choice D suggests the damage was hidden from the censors. The remaining choice means brought about by. The answer is <strong>B</strong>."
    }
  ]
}
