{
  "questionId": "7c48a6dd",
  "correctAnswer": "D",
  "section": "Reading and Writing",
  "steps": [
    {
      "title": "Find the parallel structure requirement",
      "content": "The word “and” joins two coordinate actions: “He applied... and [BLANK] them...” Both verbs must use the same grammatical form."
    },
    {
      "title": "Match with the past tense verb",
      "content": "”suspended” is the past tense form that parallels “applied.” The other choices use infinitive or participle forms that break this parallel structure. That confirms <strong>D</strong> is correct."
    }
  ]
}
