{
  "questionId": "7f935017",
  "correctAnswer": "B",
  "section": "Reading and Writing",
  "steps": [
    {
      "title": "Identify the paradox of visibility",
      "content": "The passage states the sun is “already down,” yet is “manifest in the livid tongues of fire.” The sun has set below the horizon, yet somehow becomes evident through the dramatic light display."
    },
    {
      "title": "Match the meaning to the context",
      "content": "<strong>Perceptible</strong> means something that can be perceived or seen.<br/><br/>The sun, already below the horizon, becomes visible through the colorful fire-like light effects, so “manifest” must mean perceptible.<br/><br/>The other choices describe different properties—location, accomplishment, or fading—rather than visibility.<br/><br/>That confirms <strong>B</strong> is correct."
    }
  ]
}
