{
  "questionId": "87a75825-ef1b-4b13-8fde-816390546062_19",
  "correctAnswer": "97",
  "section": "Math",
  "steps": [
    {
      "title": "Use Vieta's formulas to extract relationships",
      "content": "For any equation $x^2 + bx + c = 0$, the sum of roots equals $-b$ and their product equals $c$.<br/><br/>From $x^2+8x+13=0$: $r + s = -8$ and $rs = 13$<br/>From $x^2+12x+24=0$: $t + u = -12$ and $tu = 24$<br/><br/>The sum of the new roots is $(r+u) + (s+t) = (r+s) + (t+u) = -8 + (-12) = -20$, confirming it matches the coefficient in $x^2+20x+c=0$."
    },
    {
      "title": "Solve for exact roots using the quadratic formula",
      "content": "For $x^2+8x+13=0$: discriminant is $64 - 52 = 12$, so $$x = \\frac{-8 \\pm 2\\sqrt{3}}{2} = -4 \\pm \\sqrt{3}$$<br/>Thus $r = -4 - \\sqrt{3}$ and $s = -4 + \\sqrt{3}$.<br/><br/>For $x^2+12x+24=0$: discriminant is $144 - 96 = 48$, so $$x = \\frac{-12 \\pm 4\\sqrt{3}}{2} = -6 \\pm 2\\sqrt{3}$$<br/>Thus $t = -6 - 2\\sqrt{3}$ and $u = -6 + 2\\sqrt{3}$."
    },
    {
      "title": "Calculate $(r+u)(s+t)$ using difference of squares",
      "content": "First, compute the new roots:<br/>$$r + u = (-4 - \\sqrt{3}) + (-6 + 2\\sqrt{3}) = -10 + \\sqrt{3}$$<br/>$$s + t = (-4 + \\sqrt{3}) + (-6 - 2\\sqrt{3}) = -10 - \\sqrt{3}$$<br/>By Vieta's formulas, the constant term $c$ equals the product of roots:<br/>$$c = (r+u)(s+t) = (-10 + \\sqrt{3})(-10 - \\sqrt{3})$$<br/>Using the difference-of-squares pattern $(p + q)(p - q) = p^2 - q^2$:<br/>$$= (-10)^2 - (\\sqrt{3})^2 = 100 - 3 = 97$$<br/>Therefore, $c = 97$."
    }
  ]
}