{
  "questionId": "97ab5669",
  "correctAnswer": "B",
  "section": "Reading and Writing",
  "steps": [
    {
      "title": "Identify the key context clue",
      "content": "The phrase \u201cdoesn't have a definite idea of when\u201d combined with \u201cThis conjecture\u201d tells us Ochoa holds a belief based on incomplete information \u2014 an educated guess about something uncertain."
    },
    {
      "title": "Select the word expressing an uncertain belief",
      "content": "Speculates means forming an opinion without complete evidence. The other choices either frame this as a demand, contradict her motivation to research, or claim certainty despite her stated uncertainty. This word captures what Ochoa does \u2014 hold a belief about the future without knowing when. That matches choice B \u2014 <strong>B</strong> is correct."
    }
  ]
}