{
  "questionId": "a45480a1-becb-48bd-a285-d5366355b085_16",
  "correctAnswer": "B",
  "section": "Reading and Writing",
  "steps": [
    {
      "title": "Identify the grammatical structure needed",
      "content": "The blank is the main verb of the independent clause \u201cCordeiro ______ the library's collections.\u201d This verb must be finite (capable of functioning as the main verb of a clause) and in present tense to match the context of her current role."
    },
    {
      "title": "Apply the rule and select the correct form",
      "content": "An independent clause requires a finite main verb. Choice B (oversees) is the only finite form, in simple present tense. The other choices are non-finite verb forms\u2014participles and an infinitive\u2014that cannot function as a clause's main verb. This matches choice B \u2014 <strong>B</strong> is correct."
    }
  ]
}