{
  "questionId": "b1c9d040-6c5c-4a68-a2b7-472cc0ce4759_6",
  "correctAnswer": "C",
  "section": "Reading and Writing",
  "steps": [
    {
      "title": "Spot the setup: problem and supporting detail",
      "content": "The underlined portion identifies a characteristic that sounds like a flaw\u2014the book's \u201cabrupt ending\u201d\u2014but immediately provides a key detail: the next book \u201cpicks up neatly where <em>Master and Commander</em> leaves off.\u201d This combination signals what the text is trying to accomplish."
    },
    {
      "title": "Apply the signal to the choices",
      "content": "Choice C describes the function as offering a detail that explains why a potential flaw isn't necessarily one. This is exactly what happens: the seamless continuation with the next book provides grounds for arguing the ending isn't actually problematic. The other choices misdirect by focusing on reader preferences (A, D) or attributing a later comparison to this section (B). That matches choice C \u2014 <strong>C</strong> is correct."
    }
  ]
}