{
  "questionId": "b497f82e-d544-41ec-9ef5-cc6283f4b89f_11",
  "correctAnswer": "B",
  "section": "Reading and Writing",
  "steps": [
    {
      "title": "Identify what the question needs",
      "content": "The researchers studied Serbian customers from a developing economy and found they prioritize speedy delivery and tracking over package aesthetics. They then &quot;cautioned against applying the findings to customers generally.&quot; The blank must complete the researchers&apos; own explanation of <em>why</em> that caution is warranted &mdash; i.e., what limitation of the study prevents broad generalization."
    },
    {
      "title": "Eliminate the choices",
      "content": "<ul><li><strong>Choice A &mdash; online retailers globally should prioritize delivery speed and tracking</strong>: This applies the findings broadly, which is exactly what the researchers cautioned against. &#10007;</li><li><strong>Choice B &mdash; additional research with participants from countries of varying economic development is needed</strong>: This identifies the actual limitation &mdash; the sample came from one country with one economic profile &mdash; and calls for research that would address it. Fits the researchers&apos; caution precisely. &#10003;</li><li><strong>Choice C &mdash; the findings may not hold with a larger group of Serbian participants</strong>: The limitation is geographic and economic scope, not Serbian sample size. More Serbian respondents would not address the problem of generalizing to other countries. &#10007;</li><li><strong>Choice D &mdash; customers in wealthier countries likely value package design more</strong>: This speculates about a specific outcome without calling for further research, and the passage gives no basis for this claim. &#10007;</li></ul>That matches choice B &mdash; <strong>B</strong> is correct."
    }
  ]
}