{
  "questionId": "e580c519-9667-4b3b-8a1e-a7bec6eba694_22",
  "correctAnswer": "B",
  "section": "Reading and Writing",
  "steps": [
    {
      "title": "Identify the parallel examples",
      "content": "The passage defines ekphrastic poetry, then presents two examples: Hayden's poem about Monet's painting and Pimentel's poem about Klimt's painting. Both demonstrate the same concept \u2014 poets exploring visual art through poetry. The transition must signal this <strong>parallel relationship</strong>, not a contrast, consequence, or reversal."
    },
    {
      "title": "Match the parallel structure with the right transition",
      "content": "<em>Likewise</em> means \u201cin the same way\u201d \u2014 it signals that Pimentel's poem follows the same pattern as Hayden's, both engaging with visual art through poetry.<br/>The other choices signal different relationships \u2014 contrast (nevertheless, conversely) or causation (hence) \u2014 that don't fit parallel examples.<br/>That matches choice B \u2014 <strong>B</strong> is correct."
    }
  ]
}