{
  "questionId": "ed6c86a5-6f8d-48ff-9bc9-8a709d34d8e3_19",
  "correctAnswer": "C",
  "section": "Math",
  "steps": [
    {
      "title": "Use the perpendicularity property",
      "content": "A tangent line to a circle is perpendicular to the radius at the point of tangency. The radius goes from the center $(-2, 2)$ to the tangent point $(3, -1)$.<br/><br/>Radius slope: $$m_{\\text{radius}} = \\frac{-1-2}{3-(-2)} = \\frac{-3}{5}$$<br/>Since the tangent line is perpendicular, its slope is the negative reciprocal: $$m_{\\text{tangent}} = \\frac{5}{3}$$"
    },
    {
      "title": "Write the equation of the tangent line",
      "content": "Using point-slope form through $(3, -1)$: $$y + 1 = \\frac{5}{3}(x - 3)$$ $$y = \\frac{5}{3}x - 6$$"
    },
    {
      "title": "Evaluate all choices",
      "content": "<ul><li><strong>Choice A &mdash; '$(0, \\frac{5}{3})$'</strong>: $y = \\frac{5}{3}(0) - 6 = -6 \\neq \\frac{5}{3}$. &#10007;</li><li><strong>Choice B &mdash; '$(1, 7)$'</strong>: $y = \\frac{5}{3}(1) - 6 = -\\frac{13}{3} \\neq 7$. &#10007;</li><li><strong>Choice C &mdash; '$(6, 4)$'</strong>: $y = \\frac{5}{3}(6) - 6 = 10 - 6 = 4$. &#10003;</li><li><strong>Choice D &mdash; '$(8, 2)$'</strong>: $y = \\frac{5}{3}(8) - 6 = \\frac{40}{3} - 6 = \\frac{22}{3} \\neq 2$. &#10007;</li></ul>That matches choice C — <strong>C</strong> is correct."
    }
  ]
}
