{
  "questionId": "ff866f0f-f295-4895-b84d-a5c603adf51a_22",
  "correctAnswer": "C",
  "section": "Reading and Writing",
  "steps": [
    {
      "title": "Identify the alignment between attitude and motto",
      "content": "The key signal is that the motto \u201cWhat do I know?\u201d is an expression of the \u201cquestioning [of] his own perspective\u201d described in the prior sentence \u2014 they illustrate the same intellectual trait, so they fit together rather than contrast."
    },
    {
      "title": "Match the alignment to the choices",
      "content": "\u201dFittingly\u201d shows this natural fit \u2014 the motto appropriately exemplifies his questioning approach. The other three introduce unwanted contrast, reversal, or time shift. This matches choice C \u2014 <strong>C</strong> is correct."
    }
  ]
}